checks/__init__.py
checks/dns_check.py
serverchecks/__init__.py
serverchecks/main.py
serverchecks/server-checks.py
serverchecks/serverchecks.py
serverchecks/alerts/__init__.py
serverchecks/alerts/console_alert.py
serverchecks/alerts/matrix_alert.py
serverchecks/alerts/sendmail_alert.py
serverchecks/alerts/smtp_alert.py
serverchecks/alerts/telegram_alert.py
serverchecks/alerts/xmpp_alert.py
serverchecks/checks/__init__.py
serverchecks/checks/basicdns_check.py
serverchecks/checks/dns_check.py
serverchecks/checks/dnssec_check.py
serverchecks/checks/imap_check.py
serverchecks/checks/pop3_check.py
serverchecks/checks/smtp_check.py
serverchecks/checks/tcp_check.py
serverchecks/checks/tls_check.py
serverchecks/checks/url_check.py
serverchecks/schemas/__init__.py
serverchecks/schemas/config.yaml
serverchecks-0.5.8.dist-info/LICENSE
serverchecks-0.5.8.dist-info/METADATA
serverchecks-0.5.8.dist-info/WHEEL
serverchecks-0.5.8.dist-info/entry_points.txt
serverchecks-0.5.8.dist-info/top_level.txt
serverchecks-0.5.8.dist-info/RECORD
