Metadata-Version: 2.1
Name: serverchecks
Version: 0.5.8
Summary: UNKNOWN
Home-page: https://bitbucket.org/kravietz/serverchecks
Author: Pawel Krawczyk
Author-email: pawel.krawczyk@hush.com
License: MIT
Keywords: network ping check test dns url availability imap pop3 smtp http dnssec
Platform: UNKNOWN
Classifier: Development Status :: 3 - Alpha
Classifier: Intended Audience :: Developers
Classifier: Topic :: Software Development :: Libraries :: Python Modules
Classifier: Environment :: Web Environment
Classifier: Topic :: Internet
Classifier: License :: OSI Approved :: MIT License
Classifier: Operating System :: OS Independent
Classifier: Programming Language :: Python
Classifier: Programming Language :: Python :: 3.6
Classifier: Programming Language :: Python :: 3.7
Requires-Dist: pyyaml
Requires-Dist: yamale
Provides-Extra: dns
Requires-Dist: dnspython ; extra == 'dns'
Provides-Extra: dnssec
Requires-Dist: pycryptodomex ; extra == 'dnssec'
Requires-Dist: ecdsa ; extra == 'dnssec'
Requires-Dist: dnspython ; extra == 'dnssec'
Provides-Extra: matrix
Requires-Dist: matrix-client ; extra == 'matrix'
Provides-Extra: telegram
Requires-Dist: telethon ; extra == 'telegram'
Provides-Extra: xmpp
Requires-Dist: aioxmpp ; extra == 'xmpp'
